dcps/AimTTiPLP.py
dcps/BK9115.py
dcps/IT6500C.py
dcps/Keithley2182.py
dcps/Keithley2400.py
dcps/Keithley622x.py
dcps/Keithley6500.py
dcps/KeysightE364xA.py
dcps/PowerTestBoard.py
dcps/RigolDL3000.py
dcps/RigolDP800.py
dcps/SCPI.py
dcps/__init__.py
dcps/power_tests.py
dcps/power_tests_fix_data.py
dcps/power_tests_plot.py
dcps-0.8.0.dist-info/LICENSE
dcps-0.8.0.dist-info/METADATA
dcps-0.8.0.dist-info/WHEEL
dcps-0.8.0.dist-info/top_level.txt
dcps-0.8.0.dist-info/RECORD
