Metadata-Version: 2.1
Name: dcps
Version: 0.8.0
Summary: Control of DC Power Supplies/DC Electronic Loads/DMMs/SourceMeters through python
Home-page: https://github.com/sgoadhouse/dcps
Author: Stephen Goadhouse
Author-email: sgoadhouse@virginia.edu
Maintainer: Stephen Goadhouse
Maintainer-email: sgoadhouse@virginia.edu
License: MIT
Keywords: Rigol,DP800,DP832A,DL3000,DL3031A,AimTTI,BK,9115,Keysight,Agilent,Keithley,ITECH,E3642A,E364xA,6220,6221,2182,2182A,2400,DMM6500,6500C/D,PyVISA,VISA,SCPI,INSTRUMENT
Platform: UNKNOWN
Classifier: Development Status :: 4 - Beta
Classifier: Intended Audience :: Developers
Classifier: Intended Audience :: Education
Classifier: Intended Audience :: Science/Research
Classifier: License :: OSI Approved :: MIT License
Classifier: Programming Language :: Python
Classifier: Topic :: Scientific/Engineering
Classifier: Topic :: Scientific/Engineering :: Physics
Classifier: Topic :: Software Development
Classifier: Topic :: Software Development :: Libraries
Classifier: Topic :: Software Development :: Libraries :: Python Modules
License-File: LICENSE
